[
  {
    "id": "0v0UmoLnY3Vtg1e2ixWY",
    "date": "2024-09-05",
    "type": "reviews",
    "title": "Review of Album Y",
    "content": "Album Y by Artist Z offers a fresh and innovative sound, with each track delivering a unique listening experience.",
    "_updatedAt": "2024-09-15T03:47:52.945Z"
  },
  {
    "id": "kIorDKhX7TCwLz5xvFWT",
    "date": "2024-07-15",
    "type": "personal_insights",
    "title": "How Music Shapes My Creativity",
    "content": "Music has profoundly impacted my creative process, providing inspiration and helping me maintain focus during challenging projects.",
    "_updatedAt": "2024-09-15T03:47:52.946Z"
  }
]